geoapis/__init__.py
geoapis/geometry.py
geoapis/lidar.py
geoapis/raster.py
geoapis/vector.py
geoapis-0.3.4.dist-info/LICENSE
geoapis-0.3.4.dist-info/METADATA
geoapis-0.3.4.dist-info/WHEEL
geoapis-0.3.4.dist-info/top_level.txt
geoapis-0.3.4.dist-info/RECORD
