Metadata-Version: 2.1
Name: geoapis
Version: 0.3.4
Summary: A package for downloading geospatial data from web APIs.
Author-email: Rose pearson <rose.pearson@niwa.co.nz>
License: MIT License
Project-URL: Homepage, https://github.com/niwa/geoapis
Project-URL: Documentation, https://github.com/niwa/geoapis/wiki
Keywords: APIs,LiDAR,point clouds,vector,Geospatial data
Classifier: Development Status :: 4 - Beta
Classifier: Intended Audience :: Science/Research
Classifier: Topic :: Scientific/Engineering :: GIS
Classifier: Programming Language :: Python :: 3 :: Only
Classifier: License :: OSI Approved :: MIT License
Classifier: Operating System :: OS Independent
Requires-Python: >=3.6
License-File: LICENSE
Requires-Dist: geopandas>=0.10
Requires-Dist: requests
Requires-Dist: boto3
Requires-Dist: python-dotenv
Requires-Dist: tqdm
Requires-Dist: tomli; python_version < "3.6"
Provides-Extra: dev
Requires-Dist: black; extra == "dev"
Requires-Dist: python-dotenv; extra == "dev"
Requires-Dist: pip-tools; extra == "dev"
Requires-Dist: pytest; extra == "dev"
